push_service/__init__.py
push_service/available_addresses.py
push_service/cli.py
push_service/service.py
push_service/webui.py
push_service/templates/channel.html
push_service/templates/index.html
push_service/templates/login.html
push_service/templates/otp.html
push_service/templates/password_setup.html
push_service/templates/service_worker.js
push_service/templates/subscription.js
push_service-0.0.8.dist-info/LICENSE
push_service-0.0.8.dist-info/METADATA
push_service-0.0.8.dist-info/WHEEL
push_service-0.0.8.dist-info/entry_points.txt
push_service-0.0.8.dist-info/top_level.txt
push_service-0.0.8.dist-info/RECORD
