Metadata-Version: 2.1
Name: push-service
Version: 0.0.8
Summary: A Python implementation of the Push API
Home-page: https://github.com/aesuli/push_service
Author: Andrea Esuli
Author-email: andrea@esuli.it
License: BSD-3-Clause
Classifier: Programming Language :: Python :: 3
Classifier: Operating System :: OS Independent
Requires-Python: >=3.8
License-File: LICENSE
Requires-Dist: CherryPy ==18.10.0
Requires-Dist: ConfigArgParse ==1.7.1
Requires-Dist: Mako ==1.3.10
Requires-Dist: SQLAlchemy ==2.0.41
Requires-Dist: bcrypt ==4.3.0
Requires-Dist: psutil ==7.0.0
Requires-Dist: py-vapid ==1.9.2
Requires-Dist: pyotp ==2.9.0
Requires-Dist: pywebpush ==2.0.3
Requires-Dist: qrcode ==8.2
